.coveragerc
.hgignore
.hgtags
README.md
runtests.sh
setup.py
stylecheck.sh
tox.ini
PhilUtils.egg-info/PKG-INFO
PhilUtils.egg-info/SOURCES.txt
PhilUtils.egg-info/dependency_links.txt
PhilUtils.egg-info/top_level.txt
philutils/__init__.py
philutils/pagination.py
philutils/schema.py
tests/__init__.py
tests/test_pagination.py
tests/test_philutils.py
tests/test_schema.py