Metadata-Version: 1.0
Name: PhilUtils
Version: 1.1
Summary: Phil Zerull's tiny library of miscellaneous functions
Home-page: UNKNOWN
Author: Philip Zerull
Author-email: przerull@gmail.com
License: UNKNOWN
Platform: UNKNOWN
